{"kind":"APIResourceList","apiVersion":"v1","groupVersion":"authorization.openshift.io/v1","resources":[{"name":"clusterrolebindings","singularName":"","namespaced":false,"kind":"ClusterRoleBinding","verbs":["create","delete","get","list","patch","update"]},{"name":"clusterroles","singularName":"","namespaced":false,"kind":"ClusterRole","verbs":["create","delete","get","list","patch","update"]},{"name":"localresourceaccessreviews","singularName":"","namespaced":true,"kind":"LocalResourceAccessReview","verbs":["create"]},{"name":"localsubjectaccessreviews","singularName":"","namespaced":true,"kind":"LocalSubjectAccessReview","verbs":["create"]},{"name":"resourceaccessreviews","singularName":"","namespaced":false,"kind":"ResourceAccessReview","verbs":["create"]},{"name":"rolebindingrestrictions","singularName":"","namespaced":true,"kind":"RoleBindingRestriction","verbs":["create","delete","deletecollection","get","list","patch","update","watch"]},{"name":"rolebindings","singularName":"","namespaced":true,"kind":"RoleBinding","verbs":["create","delete","get","list","patch","update"]},{"name":"roles","singularName":"","namespaced":true,"kind":"Role","verbs":["create","delete","get","list","patch","update"]},{"name":"selfsubjectrulesreviews","singularName":"","namespaced":true,"kind":"SelfSubjectRulesReview","verbs":["create"]},{"name":"subjectaccessreviews","singularName":"","namespaced":false,"kind":"SubjectAccessReview","verbs":["create"]},{"name":"subjectrulesreviews","singularName":"","namespaced":true,"kind":"SubjectRulesReview","verbs":["create"]}]}
