{"kind":"APIResourceList","apiVersion":"v1","groupVersion":"metal3.io/v1alpha1","resources":[{"name":"baremetalhosts","singularName":"baremetalhost","namespaced":true,"kind":"BareMetalHost","verbs":["delete","deletecollection","get","list","patch","create","update","watch"],"shortNames":["bmh","bmhost"],"storageVersionHash":"6I9mpSMReUg="},{"name":"baremetalhosts/status","singularName":"","namespaced":true,"kind":"BareMetalHost","verbs":["get","patch","update"]},{"name":"provisionings","singularName":"provisioning","namespaced":false,"kind":"Provisioning","verbs":["delete","deletecollection","get","list","patch","create","update","watch"],"storageVersionHash":"MFsHXPBs+No="},{"name":"provisionings/status","singularName":"","namespaced":false,"kind":"Provisioning","verbs":["get","patch","update"]}]}
